.gitignore
LICENSE
README.rst
setup.py
foliadocserve/__init__.py
foliadocserve/client.py
foliadocserve/flat.py
foliadocserve/foliadocserve.py
foliadocserve/test.py
foliadocserve/testflat.folia.xml
foliadocserve.egg-info/PKG-INFO
foliadocserve.egg-info/SOURCES.txt
foliadocserve.egg-info/dependency_links.txt
foliadocserve.egg-info/entry_points.txt
foliadocserve.egg-info/requires.txt
foliadocserve.egg-info/top_level.txt
foliadocserve/templates/index.html