Metadata-Version: 2.1
Name: foliadocserve
Version: 0.7.8
Summary: The FoLiA Document Server is a backend HTTP service to interact with documents in the FoLiA format, a rich XML-based format for linguistic annotation (http://proycon.github.io/folia). It provides an interface to efficiently edit FoLiA documents through the FoLiA Query Language (FQL). 
Home-page: https://github.com/proycon/foliadocserve
Author: Maarten van Gompel
Author-email: proycon@anaproy.nl
License: GPL
Keywords: nlp computational_linguistics rest database document server
Classifier: Development Status :: 5 - Production/Stable
Classifier: Topic :: Text Processing :: Linguistic
Classifier: Programming Language :: Python :: 3.7
Classifier: Programming Language :: Python :: 3.8
Classifier: Programming Language :: Python :: 3.9
Classifier: Programming Language :: Python :: 3.10
Classifier: Programming Language :: Python :: 3.11
Classifier: Operating System :: POSIX
Classifier: Intended Audience :: Developers
Classifier: Intended Audience :: Science/Research
Classifier: License :: OSI Approved :: GNU General Public License v3 (GPLv3)
License-File: LICENSE
Requires-Dist: lxml>=2.2
Requires-Dist: folia>=2.5.4
Requires-Dist: pynlpl
Requires-Dist: FoLiA-tools>=2.5.2
Requires-Dist: cherrypy
Requires-Dist: Jinja2
